[
  {
    "name": "チキンフィレバーガーセット",
    "price": 850,
    "limit": -1,
    "items": {
      "チキンフィレバーガー": 1,
      "ドリンクM": 1,
      "ポテトS": 1
    }
  },
  {
    "name": "チキンフィレバーガーセット",
    "price": 900,
    "limit": -1,
    "items": {
      "チキンフィレバーガー": 1,
      "ドリンクL": 1,
      "ポテトS": 1
    }
  },
  {
    "name": "チキンフィレバーガーセット",
    "price": 1050,
    "limit": -1,
    "items": {
      "チキンフィレバーガー": 1,
      "ドリンクM": 1,
      "ポテトL": 1
    }
  },
  {
    "name": "チキンフィレバーガーセット",
    "price": 1100,
    "limit": -1,
    "items": {
      "チキンフィレバーガー": 1,
      "ドリンクL": 1,
      "ポテトL": 1
    }
  }
]
